mondata/__init__.py
mondata/config.py
mondata/enums.py
mondata/error.py
mondata/models.py
mondata/types.py
mondata/api_v2/__init__.py
mondata/api_v2/constants.py
mondata/api_v2/exceptions.py
mondata/api_v2/graphql.py
mondata/api_v2/handlers.py
mondata/api_v2/requests.py
mondata/column_value/__init__.py
mondata/column_value/base.py
mondata/column_value/complex.py
mondata/column_value/constants.py
mondata/column_value/objects.py
mondata/column_value/readonly.py
mondata/column_value/simple.py
mondata/entities/__init__.py
mondata/entities/asset.py
mondata/entities/base.py
mondata/entities/board.py
mondata/entities/client.py
mondata/entities/column.py
mondata/entities/group.py
mondata/entities/item.py
mondata/entities/objects.py
mondata/entities/update.py
mondata/entities/user.py
mondata-1.0.0a0.dist-info/LICENSE
mondata-1.0.0a0.dist-info/METADATA
mondata-1.0.0a0.dist-info/WHEEL
mondata-1.0.0a0.dist-info/top_level.txt
mondata-1.0.0a0.dist-info/RECORD
